{
  "schema_version": 1,
  "plan_id": "public_publish_plan",
  "display_name": "Public Publish Plan",
  "intent_summary": "A draft that tries to publish directly.",
  "nodes": [
    {
      "node_id": "box",
      "primitive_kind": "BoxPrimitive",
      "display_name": "Box",
      "property_values": {
        "width": { "kind": "Length", "value": 2.0 },
        "depth": { "kind": "Length", "value": 1.4 },
        "height": { "kind": "Length", "value": 1.0 },
        "edge_softness": { "kind": "Ratio", "value": 0.08 }
      },
      "role_hint": "Simple box body",
      "locked": false
    }
  ],
  "attachments": [],
  "validation_policy": {
    "require_primitive_schema_validation": true,
    "require_anchor_validation": true,
    "allow_public_catalog_publish": true
  },
  "review_tier": "Draft",
  "provenance": {
    "created_by": "InternalTool",
    "source_prompt_hash": "publish_seed",
    "source_seed_refs": ["publish_seed"],
    "created_at": "2026-07-01T00:00:00Z"
  }
}
